agri/__init__.py
agri/auth.py
agri/repo_manager.py
agri-0.1.2.dist-info/licenses/LICENSE
agri-0.1.2.dist-info/METADATA
agri-0.1.2.dist-info/WHEEL
agri-0.1.2.dist-info/top_level.txt
agri-0.1.2.dist-info/RECORD
