Metadata-Version: 2.4
Name: agri
Version: 0.1.2
Summary: Anywhere GitHub Repository Importer
Home-page: https://github.com/mmaleki92/agri
Author: Morteza Maleki
Author-email: Morteza Maleki <maleki.morteza92@gmail.com>
License: MIT
Project-URL: Homepage, https://github.com/mmaleki92/agri
Project-URL: Bug Tracker, https://github.com/mmaleki92/agri/issues
Classifier: Programming Language :: Python :: 3
Classifier: License :: OSI Approved :: MIT License
Classifier: Operating System :: OS Independent
Classifier: Programming Language :: Python :: 3.8
Classifier: Programming Language :: Python :: 3.9
Classifier: Programming Language :: Python :: 3.10
Classifier: Programming Language :: Python :: 3.11
Classifier: Programming Language :: Python :: 3.12
Requires-Python: >=3.8
License-File: LICENSE
Requires-Dist: gitpython
Requires-Dist: keyring
Requires-Dist: tqdm
Dynamic: author
Dynamic: home-page
Dynamic: license-file
Dynamic: requires-python
